color_transfer/__init__.py
color_transfer/cli.py
color_transfer/main.py
color_transfer/py.typed
color_transfer/libs/__init__.py
color_transfer/libs/base_transfer.py
color_transfer/libs/emd_transfer.py
color_transfer/libs/lab_transfer.py
color_transfer/libs/lhm_transfer.py
color_transfer/libs/mean_std_transfer.py
color_transfer/libs/pccm_transfer.py
color_transfer/libs/pdf_transfer.py
color_transfer/libs/sinkhorn_transfer.py
color_transfer/libs/transfer_factory.py
color_transfer/utils/__init__.py
color_transfer/utils/image_utils.py
chromasoul_color_transfer-1.0.3.dist-info/METADATA
chromasoul_color_transfer-1.0.3.dist-info/WHEEL
chromasoul_color_transfer-1.0.3.dist-info/entry_points.txt
chromasoul_color_transfer-1.0.3.dist-info/licenses/LICENSE
chromasoul_color_transfer-1.0.3.dist-info/RECORD
