Metadata-Version: 2.4
Name: chromasoul_color_transfer
Version: 1.0.3
Summary: ColorTransfer provides a suite of tools for color migration tasks.
Author-email: XIAODUOLU <lxd0705@163.com>
License-File: LICENSE
Requires-Python: >=3.12
Requires-Dist: black>=25.9.0
Requires-Dist: numpy==1.26
Requires-Dist: opencv-python>=4.11.0.86
Requires-Dist: pot>=0.9.6.post1
